Metadata-Version: 2.1
Name: odoo-addon-api-common-base
Version: 16.0.1.0.0
Summary: REST API Common Controller
Home-page: https://gitlab.com/somitcoop/erp-research/odoo-helpdesk
Author: Som It Cooperatiu SCCL, Som Connexió SCCL, Odoo Community Association (OCA)
Author-email: support@odoo-community.org
License: AGPL-3
Classifier: Programming Language :: Python
Classifier: Framework :: Odoo
Classifier: Framework :: Odoo :: 16.0
Classifier: License :: OSI Approved :: GNU Affero General Public License v3
Requires-Python: >=3.10
Requires-Dist: odoo-addon-auth-api-key <16.1dev,>=16.0dev
Requires-Dist: odoo-addon-base-rest <16.1dev,>=16.0dev
Requires-Dist: odoo <16.1dev,>=16.0a
